{
    "symbol": "ESSA",
    "name": "ESSA Bancorp, Inc.",
    "sector": "Financial",
    "industry": "Banks - Regional",
    "country": "USA",
    "exchange": "NASD",
    "statements": {
        "Income Statement": {
            "Dates": [
                "TTM",
                "9/30/2022",
                "9/30/2021",
                "9/30/2020",
                "9/30/2019",
                "9/30/2018",
                "9/30/2017",
                "9/30/2016"
            ],
            "Interest Income": [
                "62.81",
                "62.81",
                "58.69"
            ],
            "Total Interest Expenses": [
                "3.04",
                "3.04",
                "5.79"
            ],
            "Net Interest Income": [
                "59.77",
                "59.77",
                "52.89"
            ],
            "Loan Loss Provision": [
                "0.00",
                "0.00",
                "2.70"
            ],
            "Net Interest Income After Loan Loss Provision": [
                "59.77",
                "59.77",
                "50.19"
            ],
            "Non-Interest Income": [
                "8.51",
                "8.51",
                "11.49"
            ],
            "Non-Interest Expense": [
                "-43.28",
                "-43.28",
                "-41.79"
            ],
            "Net Income Before Taxes": [
                "25.00",
                "25.00",
                "19.90"
            ],
            "Provision for Income Taxes": [
                "4.93",
                "4.93",
                "3.47"
            ],
            "Net Income": [
                "20.07",
                "20.07",
                "16.42"
            ],
            "Income Avail. to Common Excl. Extraord.": [
                "20.07",
                "20.07",
                "16.42"
            ],
            "Income Avail. to Common Incl. Extraord.": [
                "20.07",
                "20.07",
                "16.42"
            ],
            "Diluted Average Shares": [
                "9.76",
                "9.77",
                "9.95"
            ],
            "Diluted EPS Excl. Extraord.": [
                "2.05585",
                "2.05527",
                "1.65107"
            ],
            "Diluted EPS Incl. Extraord.": [
                "2.05585",
                "2.05527",
                "1.65107"
            ]
        },
        "Balance Sheet": {
            "Dates": [
                "9/30/2022",
                "9/30/2021",
                "9/30/2020",
                "9/30/2019",
                "9/30/2018",
                "9/30/2017",
                "9/30/2016",
                "9/30/2015"
            ],
            "Cash & Due From Banks": [
                "19.97",
                "146.84",
                "101.45"
            ],
            "Net Loans": [
                "1435.78",
                "1340.85",
                "1418.18"
            ],
            "Property Plant And Equipment - Net": [
                "19.20",
                "19.83",
                "21.31"
            ],
            "Goodwill Net": [
                "13.80",
                "13.80",
                "13.80"
            ],
            "Intangibles Net": [
                "0.28",
                "0.52",
                "0.79"
            ],
            "Other Long Term Assets": [
                "5.38",
                "4.61",
                "5.99"
            ],
            "Total Assets": [
                "1861.82",
                "1861.44",
                "1893.52"
            ],
            "Accrued Expenses": [
                "6.28",
                "6.37",
                "7.16"
            ],
            "Total Deposits": [
                "1380.02",
                "1636.12",
                "1543.70"
            ],
            "Other Bearing Liabilities": [
                "",
                "0.00",
                "14.16"
            ],
            "Total Short Term Borrowings": [
                "230.81",
                "0.00",
                "111.71"
            ],
            "Current Port. of LT Debt/Capital Leases": [
                "",
                "",
                ""
            ],
            "Long Term Debt": [
                "",
                "",
                ""
            ],
            "Total Long Term Debt": [
                "0.00",
                "0.00",
                "0.00"
            ],
            "Total Debt": [
                "230.81",
                "0.00",
                "111.71"
            ],
            "Other Liabilities": [
                "32.37",
                "17.13",
                "25.38"
            ],
            "Total Liabilities": [
                "1649.48",
                "1659.61",
                "1702.12"
            ],
            "Common Stock": [
                "0.18",
                "0.18",
                "0.18"
            ],
            "Additional Paid-In Capital": [
                "182.17",
                "181.66",
                "181.49"
            ],
            "Retained Earnings": [
                "139.14",
                "124.34",
                "112.61"
            ],
            "Unrealized Gain (Loss)": [
                "-13.88",
                "1.96",
                "3.17"
            ],
            "Other Equity": [
                "10.98",
                "-1.28",
                "-7.22"
            ],
            "Total Equity": [
                "212.34",
                "201.82",
                "191.40"
            ],
            "Total Liabilities and Equity": [
                "1861.82",
                "1861.44",
                "1893.52"
            ],
            "Total Common Shares Outstanding": [
                "10.37",
                "10.46",
                "10.88"
            ],
            "Full-Time Employees": [
                "230",
                "234",
                "234"
            ],
            "Number of Common Shareholders": [
                "1656",
                "1691",
                "1747"
            ]
        },
        "Cash Flow": {
            "Dates": [
                "TTM",
                "9/30/2022",
                "9/30/2021",
                "9/30/2020",
                "9/30/2019",
                "9/30/2018",
                "9/30/2017",
                "9/30/2016"
            ],
            "Net Income": [
                "20.07",
                "20.07",
                "16.42"
            ],
            "Depreciation/Depletion": [
                "1.07",
                "1.07",
                "1.05"
            ],
            "Amortization": [
                "0.24",
                "0.24",
                "0.27"
            ],
            "Deferred Taxes": [
                "-0.19",
                "-0.19",
                "1.21"
            ],
            "Non-Cash Items": [
                "1.80",
                "1.80",
                "0.70"
            ],
            "Changes in Working Capital": [
                "-0.29",
                "-0.29",
                "-0.28"
            ],
            "Cash from Operating Activities": [
                "22.71",
                "22.71",
                "19.38"
            ],
            "Capital Expenditures": [
                "-0.57",
                "-0.57",
                "-0.40"
            ],
            "Other Investing Cash Flow Items": [
                "-127.56",
                "-127.56",
                "32.19"
            ],
            "Cash from Investing Activities": [
                "-128.13",
                "-128.13",
                "31.79"
            ],
            "Financing Cash Flow Items": [
                "-249.24",
                "-249.24",
                "75.35"
            ],
            "Total Cash Dividends Paid": [
                "-5.27",
                "-5.27",
                "-4.69"
            ],
            "Issuance (Retirement) of Stock": [
                "-1.88",
                "-1.88",
                "-7.08"
            ],
            "Issuance (Retirement) of Debt": [
                "230.81",
                "230.81",
                "-111.71"
            ],
            "Cash from Financing Activities": [
                "-25.59",
                "-25.59",
                "-48.14"
            ],
            "Foreign Exchange Effects": [
                "",
                "",
                ""
            ],
            "Net Cash - Beginning Balance": [
                "",
                "158.95",
                "155.92"
            ],
            "Net Cash - Ending Balance": [
                "",
                "27.94",
                "158.95"
            ],
            "Net Change in Cash": [
                "-131.01",
                "-131.01",
                "3.03"
            ],
            "Cash Interest Paid": [
                "2.89",
                "2.89",
                "6.38"
            ],
            "Cash Taxes Paid": [
                "3.45",
                "3.45",
                "0.00"
            ]
        }
    }
}