{
    "symbol": "AMBO",
    "name": "Ambow Education Holding Ltd.",
    "sector": "Consumer Defensive",
    "industry": "Education & Training Services",
    "country": "China",
    "exchange": "AMEX",
    "statements": {
        "Income Statement": {
            "Dates": [
                "TTM",
                "12/31/2021",
                "12/31/2020",
                "12/31/2019",
                "12/31/2018",
                "12/31/2017",
                "12/31/2016",
                "12/31/2015"
            ],
            "Total Revenue": [
                "399.06",
                "496.88",
                "531.98"
            ],
            "Cost of Revenue": [
                "286.13",
                "339.56",
                "387.49"
            ],
            "Gross Profit": [
                "112.93",
                "157.32",
                "144.49"
            ],
            "Selling General and Administrative": [
                "222.98",
                "222.48",
                "226.64"
            ],
            "Research and Development": [
                "15.49",
                "14.49",
                "5.70"
            ],
            "Unusual Expense/Income": [
                "-10.11",
                "-12.26",
                "-12.22"
            ],
            "Total Operating Expense": [
                "514.49",
                "567.24",
                "607.61"
            ],
            "Operating Income": [
                "-115.42",
                "-70.37",
                "-75.63"
            ],
            "Interest Income Net": [
                "10.51",
                "11.61",
                "13.96"
            ],
            "Other Income Net": [
                "3.93",
                "1.66",
                "-1.24"
            ],
            "Net Income Before Taxes": [
                "-100.99",
                "-57.10",
                "-62.92"
            ],
            "Provision for Income Taxes": [
                "-5.21",
                "-59.11",
                "1.06"
            ],
            "Net Income": [
                "-94.13",
                "3.00",
                "-62.71"
            ],
            "Income Avail. to Common Excl. Extraord.": [
                "-94.13",
                "3.00",
                "-62.71"
            ],
            "Income Avail. to Common Incl. Extraord.": [
                "-94.13",
                "3.00",
                "-62.71"
            ],
            "Diluted Average Shares": [
                "45.98",
                "46.65",
                "44.37"
            ],
            "Diluted EPS Excl. Extraord.": [
                "-1.96406",
                "0.06434",
                "-1.41331"
            ],
            "Diluted EPS Incl. Extraord.": [
                "-1.96406",
                "0.06434",
                "-1.41331"
            ]
        },
        "Balance Sheet": {
            "Dates": [
                "12/31/2021",
                "12/31/2020",
                "12/31/2019",
                "12/31/2018",
                "12/31/2017",
                "12/31/2016",
                "12/31/2015",
                "12/31/2014"
            ],
            "Cash and Equivalents": [
                "157.40",
                "118.82",
                "157.60"
            ],
            "Short Term Investments": [
                "17.76",
                "162.85",
                "88.49"
            ],
            "Cash and Short Term Investments": [
                "175.16",
                "281.68",
                "246.09"
            ],
            "Accounts Receivable - Trade Net": [
                "28.64",
                "23.93",
                "20.26"
            ],
            "Total Receivables Net": [
                "63.63",
                "58.93",
                "20.26"
            ],
            "Total Inventory": [
                "",
                "",
                ""
            ],
            "Total Current Assets": [
                "448.31",
                "424.13",
                "399.64"
            ],
            "Property Plant And Equipment - Gross": [
                "421.68",
                "535.30",
                ""
            ],
            "Property Plant And Equipment - Net": [
                "327.57",
                "397.95",
                "421.27"
            ],
            "Goodwill Net": [
                "21.91",
                "25.71",
                "60.35"
            ],
            "Intangibles Net": [
                "29.99",
                "56.52",
                "58.37"
            ],
            "Long Term Investments": [
                "",
                "1.74",
                ""
            ],
            "Other Long Term Assets": [
                "128.67",
                "129.94",
                "81.17"
            ],
            "Total Assets": [
                "970.16",
                "1049.72",
                "1020.80"
            ],
            "Accounts Payable": [
                "29.47",
                "19.42",
                "14.72"
            ],
            "Accrued Expenses": [
                "265.32",
                "263.29",
                "246.47"
            ],
            "Notes Payable/Short Term Debt": [
                "10.10",
                "10.00",
                "0.00"
            ],
            "Current Port. of LT Debt/Capital Leases": [
                "",
                "",
                ""
            ],
            "Other Current liabilities": [
                "298.33",
                "350.88",
                "347.80"
            ],
            "Total Current Liabilities": [
                "603.22",
                "643.60",
                "608.98"
            ],
            "Long Term Debt": [
                "0.00",
                "9.59",
                ""
            ],
            "Capital Lease Obligations": [
                "",
                "",
                ""
            ],
            "Total Long Term Debt": [
                "0.00",
                "9.59",
                "0.00"
            ],
            "Total Debt": [
                "10.10",
                "19.59",
                "0.00"
            ],
            "Other Liabilities": [
                "220.26",
                "255.37",
                "248.22"
            ],
            "Total Liabilities": [
                "823.97",
                "906.60",
                "856.52"
            ],
            "Common Stock": [
                "0.89",
                "0.88",
                "0.82"
            ],
            "Additional Paid-In Capital": [
                "3545.95",
                "3545.07",
                "3508.74"
            ],
            "Retained Earnings": [
                "-3411.93",
                "-3414.94",
                "-3351.63"
            ],
            "Unrealized Gain (Loss)": [
                "",
                "",
                ""
            ],
            "Other Equity": [
                "11.29",
                "12.10",
                "6.34"
            ],
            "Total Equity": [
                "146.20",
                "143.12",
                "164.28"
            ],
            "Total Liabilities and Equity": [
                "970.16",
                "1049.72",
                "1020.80"
            ],
            "Total Common Shares Outstanding": [
                "46.68",
                "46.63",
                "43.57"
            ],
            "Full-Time Employees": [
                "1088",
                "1809",
                ""
            ],
            "Number of Common Shareholders": [
                "",
                "",
                ""
            ]
        },
        "Cash Flow": {
            "Dates": [
                "TTM",
                "12/31/2021",
                "12/31/2020",
                "12/31/2019",
                "12/31/2018",
                "12/31/2017",
                "12/31/2016",
                "12/31/2015"
            ],
            "Net Income": [
                "2.00",
                "2.00",
                "-63.98"
            ],
            "Depreciation/Depletion": [
                "53.64",
                "53.64",
                "68.25"
            ],
            "Amortization": [
                "",
                "",
                ""
            ],
            "Deferred Taxes": [
                "10.94",
                "10.94",
                "-4.85"
            ],
            "Non-Cash Items": [
                "-1.49",
                "-1.49",
                "-2.72"
            ],
            "Changes in Working Capital": [
                "-156.74",
                "-138.76",
                "8.12"
            ],
            "Cash from Operating Activities": [
                "-91.64",
                "-73.66",
                "4.81"
            ],
            "Capital Expenditures": [
                "-19.62",
                "-19.83",
                "-10.86"
            ],
            "Other Investing Cash Flow Items": [
                "-17.25",
                "127.02",
                "-87.65"
            ],
            "Cash from Investing Activities": [
                "-36.87",
                "107.20",
                "-98.51"
            ],
            "Financing Cash Flow Items": [
                "",
                "0.10",
                "0.00"
            ],
            "Total Cash Dividends Paid": [
                "",
                "",
                ""
            ],
            "Issuance (Retirement) of Stock": [
                "0.00",
                "0.00",
                "35.58"
            ],
            "Issuance (Retirement) of Debt": [
                "22.57",
                "5.74",
                "19.59"
            ],
            "Cash from Financing Activities": [
                "22.82",
                "5.84",
                "55.17"
            ],
            "Foreign Exchange Effects": [
                "-0.24",
                "0.21",
                "0.57"
            ],
            "Net Cash - Beginning Balance": [
                "",
                "119.64",
                "157.60"
            ],
            "Net Cash - Ending Balance": [
                "",
                "159.22",
                "119.64"
            ],
            "Net Change in Cash": [
                "-105.93",
                "39.58",
                "-37.95"
            ],
            "Cash Interest Paid": [
                "0.63",
                "0.32",
                "0.13"
            ],
            "Cash Taxes Paid": [
                "0.06",
                "1.28",
                "2.66"
            ]
        }
    }
}