{
    "symbol": "ZENV",
    "name": "Zenvia Inc.",
    "sector": "Technology",
    "industry": "Software - Infrastructure",
    "country": "Brazil",
    "exchange": "NASD",
    "statements": {
        "Income Statement": {
            "Dates": [
                "TTM",
                "12/31/2021",
                "12/31/2020",
                "12/31/2019",
                "12/31/2018"
            ],
            "Total Revenue": [
                "772.09",
                "612.32",
                "429.70"
            ],
            "Cost of Revenue": [
                "516.30",
                "431.42",
                "325.87"
            ],
            "Gross Profit": [
                "255.79",
                "180.91",
                "103.83"
            ],
            "Selling General and Administrative": [
                "240.73",
                "241.67",
                "100.99"
            ],
            "Research and Development": [
                "76.80",
                "46.31",
                "15.64"
            ],
            "Unusual Expense/Income": [
                "",
                "",
                "1.67"
            ],
            "Total Operating Expense": [
                "816.18",
                "658.82",
                "451.81"
            ],
            "Operating Income": [
                "-44.09",
                "-46.50",
                "-22.11"
            ],
            "Interest Income Net": [
                "-28.71",
                "-12.82",
                "-3.57"
            ],
            "Other Income Net": [
                "-0.68",
                "-6.15",
                "-3.80"
            ],
            "Net Income Before Taxes": [
                "-73.49",
                "-65.47",
                "-29.47"
            ],
            "Provision for Income Taxes": [
                "-34.96",
                "-20.82",
                "-8.04"
            ],
            "Net Income": [
                "-38.49",
                "-44.65",
                "-21.43"
            ],
            "Income Avail. to Common Excl. Extraord.": [
                "-38.49",
                "-44.65",
                "-21.43"
            ],
            "Income Avail. to Common Incl. Extraord.": [
                "-38.49",
                "-44.65",
                "-21.43"
            ],
            "Diluted Average Shares": [
                "43.03",
                "41.32",
                "39.29"
            ],
            "Diluted EPS Excl. Extraord.": [
                "-1.05006",
                "-1.08038",
                "-0.54542"
            ],
            "Diluted EPS Incl. Extraord.": [
                "-1.05006",
                "-1.08038",
                "-0.54542"
            ]
        },
        "Balance Sheet": {
            "Dates": [
                "12/31/2021",
                "12/31/2020",
                "12/31/2019"
            ],
            "Cash and Equivalents": [
                "",
                "",
                ""
            ],
            "Short Term Investments": [
                "346.76",
                "46.88",
                "0.51"
            ],
            "Cash and Short Term Investments": [
                "582.23",
                "59.98",
                "12.34"
            ],
            "Accounts Receivable - Trade Net": [
                "142.41",
                "86.01",
                "62.14"
            ],
            "Total Receivables Net": [
                "158.34",
                "90.91",
                "64.84"
            ],
            "Total Inventory": [
                "",
                "",
                ""
            ],
            "Total Current Assets": [
                "766.06",
                "154.69",
                "79.09"
            ],
            "Property Plant And Equipment - Gross": [
                "30.12",
                "23.12",
                "28.53"
            ],
            "Property Plant And Equipment - Net": [
                "15.73",
                "12.49",
                "17.50"
            ],
            "Goodwill Net": [
                "813.91",
                "163.39",
                "78.78"
            ],
            "Intangibles Net": [
                "236.44",
                "118.08",
                "70.33"
            ],
            "Long Term Investments": [
                "7.00",
                "2.23",
                "3.29"
            ],
            "Other Long Term Assets": [
                "4.58",
                "1.93",
                "0.00"
            ],
            "Total Assets": [
                "1843.85",
                "452.85",
                "248.98"
            ],
            "Accounts Payable": [
                "144.42",
                "91.12",
                "39.22"
            ],
            "Accrued Expenses": [
                "21.93",
                "6.68",
                "6.75"
            ],
            "Notes Payable/Short Term Debt": [
                "0.00",
                "0.00",
                "0.00"
            ],
            "Current Port. of LT Debt/Capital Leases": [
                "66.64",
                "57.31",
                "20.38"
            ],
            "Other Current liabilities": [
                "196.90",
                "71.33",
                "8.42"
            ],
            "Total Current Liabilities": [
                "429.88",
                "226.44",
                "74.78"
            ],
            "Long Term Debt": [
                "143.72",
                "42.78",
                "45.65"
            ],
            "Capital Lease Obligations": [
                "2.04",
                "1.65",
                "4.60"
            ],
            "Total Long Term Debt": [
                "145.76",
                "44.43",
                "50.25"
            ],
            "Total Debt": [
                "212.40",
                "101.73",
                "70.64"
            ],
            "Other Liabilities": [
                "63.25",
                "43.85",
                "7.85"
            ],
            "Total Liabilities": [
                "640.65",
                "337.51",
                "149.65"
            ],
            "Common Stock": [
                "957.52",
                "130.29",
                "93.88"
            ],
            "Additional Paid-In Capital": [
                "",
                "",
                ""
            ],
            "Retained Earnings": [
                "211.04",
                "-15.98",
                "5.45"
            ],
            "Unrealized Gain (Loss)": [
                "",
                "",
                ""
            ],
            "Other Equity": [
                "34.64",
                "1.03",
                "0.00"
            ],
            "Total Equity": [
                "1203.20",
                "115.35",
                "99.34"
            ],
            "Total Liabilities and Equity": [
                "1843.85",
                "452.85",
                "248.98"
            ],
            "Total Common Shares Outstanding": [
                "41.32",
                "39.29",
                "39.29"
            ],
            "Full-Time Employees": [
                "1085",
                "470",
                "226"
            ],
            "Number of Common Shareholders": [
                "",
                "",
                ""
            ]
        },
        "Cash Flow": {
            "Dates": [
                "TTM",
                "12/31/2021",
                "12/31/2020",
                "12/31/2019",
                "12/31/2018"
            ],
            "Net Income": [
                "-38.53",
                "-44.65",
                "-21.43"
            ],
            "Depreciation/Depletion": [
                "68.47",
                "41.13",
                "27.29"
            ],
            "Amortization": [
                "",
                "",
                ""
            ],
            "Deferred Taxes": [
                "",
                "",
                ""
            ],
            "Non-Cash Items": [
                "-32.35",
                "-21.37",
                "30.81"
            ],
            "Changes in Working Capital": [
                "102.56",
                "-72.37",
                "9.48"
            ],
            "Cash from Operating Activities": [
                "100.14",
                "-97.26",
                "46.14"
            ],
            "Capital Expenditures": [
                "-39.98",
                "-19.41",
                "-17.31"
            ],
            "Other Investing Cash Flow Items": [
                "-268.47",
                "-331.64",
                "-44.28"
            ],
            "Cash from Investing Activities": [
                "-308.45",
                "-351.05",
                "-61.59"
            ],
            "Financing Cash Flow Items": [
                "-164.21",
                "-142.10",
                "0.00"
            ],
            "Total Cash Dividends Paid": [
                "",
                "",
                ""
            ],
            "Issuance (Retirement) of Stock": [
                "-5.54",
                "1031.36",
                "36.41"
            ],
            "Issuance (Retirement) of Debt": [
                "-102.17",
                "45.78",
                "25.64"
            ],
            "Cash from Financing Activities": [
                "-271.92",
                "935.03",
                "62.05"
            ],
            "Foreign Exchange Effects": [
                "-8.58",
                "35.53",
                "1.03"
            ],
            "Net Cash - Beginning Balance": [
                "",
                "59.98",
                "12.34"
            ],
            "Net Cash - Ending Balance": [
                "",
                "582.23",
                "59.98"
            ],
            "Net Change in Cash": [
                "-488.81",
                "522.25",
                "47.64"
            ],
            "Cash Interest Paid": [
                "30.02",
                "17.93",
                "5.23"
            ],
            "Cash Taxes Paid": [
                "0.40",
                "1.45",
                "1.74"
            ]
        }
    }
}