{
    "symbol": "BCSF",
    "name": "Bain Capital Specialty Finance, Inc.",
    "sector": "Financial",
    "industry": "Asset Management",
    "country": "USA",
    "exchange": "NYSE",
    "statements": {
        "Income Statement": {
            "Dates": [
                "TTM",
                "12/31/2021",
                "12/31/2020",
                "12/31/2019",
                "12/31/2018",
                "12/31/2017",
                "12/31/2016"
            ],
            "Total Revenue": [
                "212.72",
                "197.39",
                "194.46"
            ],
            "Cost of Revenue": [
                "102.23",
                "103.76",
                "102.27"
            ],
            "Gross Profit": [
                "110.49",
                "93.64",
                "92.19"
            ],
            "Selling General and Administrative": [
                "5.94",
                "5.76",
                "6.12"
            ],
            "Research and Development": [
                "",
                "",
                ""
            ],
            "Unusual Expense/Income": [
                "",
                "",
                ""
            ],
            "Total Operating Expense": [
                "108.18",
                "109.52",
                "108.40"
            ],
            "Operating Income": [
                "104.54",
                "87.87",
                "86.06"
            ],
            "Interest Income Net": [
                "-20.17",
                "32.07",
                "-77.55"
            ],
            "Other Income Net": [
                "",
                "",
                ""
            ],
            "Net Income Before Taxes": [
                "84.37",
                "119.94",
                "8.51"
            ],
            "Provision for Income Taxes": [
                "",
                "0.13",
                "0.23"
            ],
            "Net Income": [
                "84.24",
                "119.81",
                "8.28"
            ],
            "Income Avail. to Common Excl. Extraord.": [
                "84.24",
                "119.81",
                "8.28"
            ],
            "Income Avail. to Common Incl. Extraord.": [
                "84.24",
                "119.81",
                "8.28"
            ],
            "Diluted Average Shares": [
                "64.56",
                "64.56",
                "58.67"
            ],
            "Diluted EPS Excl. Extraord.": [
                "1.30479",
                "1.85568",
                "0.14109"
            ],
            "Diluted EPS Incl. Extraord.": [
                "1.30479",
                "1.85568",
                "0.14109"
            ]
        },
        "Balance Sheet": {
            "Dates": [
                "12/31/2021",
                "12/31/2020",
                "12/31/2019",
                "12/31/2018",
                "12/31/2017",
                "12/31/2016"
            ],
            "Cash and Equivalents": [
                "87.44",
                "53.70",
                "36.53"
            ],
            "Short Term Investments": [
                "",
                "",
                ""
            ],
            "Cash and Short Term Investments": [
                "117.42",
                "54.68",
                "37.34"
            ],
            "Accounts Receivable - Trade Net": [
                "30.33",
                "5.93",
                "21.99"
            ],
            "Total Receivables Net": [
                "48.73",
                "13.52",
                "22.95"
            ],
            "Total Inventory": [
                "",
                "",
                ""
            ],
            "Total Current Assets": [
                "",
                "",
                ""
            ],
            "Property Plant And Equipment - Gross": [
                "",
                "",
                ""
            ],
            "Property Plant And Equipment - Net": [
                "",
                "",
                ""
            ],
            "Goodwill Net": [
                "",
                "",
                ""
            ],
            "Intangibles Net": [
                "",
                "",
                ""
            ],
            "Long Term Investments": [
                "2294.43",
                "2484.49",
                "2528.09"
            ],
            "Other Long Term Assets": [
                "88.34",
                "30.16",
                "34.69"
            ],
            "Total Assets": [
                "2571.19",
                "2603.49",
                "2645.55"
            ],
            "Accounts Payable": [
                "",
                "",
                ""
            ],
            "Accrued Expenses": [
                "7.06",
                "8.22",
                "15.53"
            ],
            "Notes Payable/Short Term Debt": [
                "0.00",
                "0.00",
                "0.00"
            ],
            "Current Port. of LT Debt/Capital Leases": [
                "",
                "",
                ""
            ],
            "Other Current liabilities": [
                "43.06",
                "43.03",
                "33.58"
            ],
            "Total Current Liabilities": [
                "",
                "",
                ""
            ],
            "Long Term Debt": [
                "1414.98",
                "1458.36",
                "1574.63"
            ],
            "Capital Lease Obligations": [
                "",
                "",
                ""
            ],
            "Total Long Term Debt": [
                "1414.98",
                "1458.36",
                "1574.63"
            ],
            "Total Debt": [
                "1414.98",
                "1458.36",
                "1574.63"
            ],
            "Other Liabilities": [
                "0.00",
                "22.61",
                "1.25"
            ],
            "Total Liabilities": [
                "1471.19",
                "1535.49",
                "1627.15"
            ],
            "Common Stock": [
                "0.07",
                "0.07",
                "0.05"
            ],
            "Additional Paid-In Capital": [
                "1168.38",
                "1166.45",
                "1038.34"
            ],
            "Retained Earnings": [
                "-68.44",
                "-98.51",
                "-20.00"
            ],
            "Unrealized Gain (Loss)": [
                "",
                "",
                ""
            ],
            "Other Equity": [
                "",
                "",
                ""
            ],
            "Total Equity": [
                "1100.01",
                "1068.00",
                "1018.40"
            ],
            "Total Liabilities and Equity": [
                "2571.19",
                "2603.49",
                "2645.55"
            ],
            "Total Common Shares Outstanding": [
                "64.56",
                "64.56",
                "52.66"
            ],
            "Full-Time Employees": [
                "0",
                "0",
                "0"
            ],
            "Number of Common Shareholders": [
                "113",
                "109",
                "120"
            ]
        },
        "Cash Flow": {
            "Dates": [
                "TTM",
                "12/31/2021",
                "12/31/2020",
                "12/31/2019",
                "12/31/2018",
                "12/31/2017",
                "12/31/2016"
            ],
            "Net Income": [
                "84.24",
                "119.81",
                "8.28"
            ],
            "Depreciation/Depletion": [
                "",
                "",
                ""
            ],
            "Amortization": [
                "",
                "",
                ""
            ],
            "Deferred Taxes": [
                "",
                "",
                ""
            ],
            "Non-Cash Items": [
                "40.58",
                "-55.78",
                "80.80"
            ],
            "Changes in Working Capital": [
                "-435.60",
                "201.53",
                "0.34"
            ],
            "Cash from Operating Activities": [
                "-310.78",
                "265.55",
                "89.42"
            ],
            "Capital Expenditures": [
                "",
                "",
                ""
            ],
            "Other Investing Cash Flow Items": [
                "",
                "",
                ""
            ],
            "Cash from Investing Activities": [
                "",
                "",
                ""
            ],
            "Financing Cash Flow Items": [
                "-12.50",
                "-14.05",
                "-8.64"
            ],
            "Total Cash Dividends Paid": [
                "-87.81",
                "-87.81",
                "-86.25"
            ],
            "Issuance (Retirement) of Stock": [
                "",
                "",
                "131.92"
            ],
            "Issuance (Retirement) of Debt": [
                "379.51",
                "-36.78",
                "-113.54"
            ],
            "Cash from Financing Activities": [
                "279.21",
                "-138.63",
                "-76.52"
            ],
            "Foreign Exchange Effects": [
                "-2.51",
                "-5.04",
                "-0.04"
            ],
            "Net Cash - Beginning Balance": [
                "",
                "81.70",
                "68.85"
            ],
            "Net Cash - Ending Balance": [
                "",
                "203.58",
                "81.70"
            ],
            "Net Change in Cash": [
                "-34.08",
                "121.88",
                "12.86"
            ],
            "Cash Interest Paid": [
                "44.04",
                "46.78",
                "67.94"
            ],
            "Cash Taxes Paid": [
                "0.00",
                "0.24",
                "0.00"
            ]
        }
    }
}