{
    "symbol": "PIII",
    "name": "P3 Health Partners Inc.",
    "sector": "Healthcare",
    "industry": "Medical Care Facilities",
    "country": "USA",
    "exchange": "NASD",
    "statements": {
        "Income Statement": {
            "Dates": [
                "TTM",
                "12/31/2021",
                "12/31/2020",
                "12/31/2019",
                "12/31/2018"
            ],
            "Total Revenue": [
                "969.12",
                "637.36",
                "485.54"
            ],
            "Cost of Revenue": [
                "988.15",
                "659.34",
                "485.51"
            ],
            "Gross Profit": [
                "-19.03",
                "-21.98",
                "0.03"
            ],
            "Selling General and Administrative": [
                "185.36",
                "119.41",
                "54.89"
            ],
            "Research and Development": [
                "",
                "",
                ""
            ],
            "Unusual Expense/Income": [
                "",
                "",
                ""
            ],
            "Total Operating Expense": [
                "2120.88",
                "825.31",
                "520.66"
            ],
            "Operating Income": [
                "-1151.76",
                "-187.95",
                "-35.12"
            ],
            "Interest Income Net": [
                "-6.11",
                "-11.00",
                "-9.97"
            ],
            "Other Income Net": [
                "10.06",
                "-5.39",
                "-0.29"
            ],
            "Net Income Before Taxes": [
                "-1147.82",
                "-204.34",
                "-45.38"
            ],
            "Provision for Income Taxes": [
                "",
                "0.00",
                ""
            ],
            "Net Income": [
                "-254.88",
                "-156.48",
                "-41.07"
            ],
            "Income Avail. to Common Excl. Extraord.": [
                "-254.88",
                "-156.48",
                "-41.07"
            ],
            "Income Avail. to Common Incl. Extraord.": [
                "-254.88",
                "-156.48",
                "-41.07"
            ],
            "Diluted Average Shares": [
                "41.58",
                "41.58",
                "243.60"
            ],
            "Diluted EPS Excl. Extraord.": [
                "-6.13007",
                "-3.76348",
                "-0.16861"
            ],
            "Diluted EPS Incl. Extraord.": [
                "-6.13007",
                "-3.76348",
                "-0.16861"
            ]
        },
        "Balance Sheet": {
            "Dates": [
                "12/31/2021",
                "12/31/2020",
                "12/31/2019"
            ],
            "Cash and Equivalents": [
                "",
                "",
                ""
            ],
            "Short Term Investments": [
                "",
                "",
                ""
            ],
            "Cash and Short Term Investments": [
                "140.48",
                "36.26",
                "32.59"
            ],
            "Accounts Receivable - Trade Net": [
                "51.34",
                "39.11",
                "17.97"
            ],
            "Total Receivables Net": [
                "52.07",
                "39.25",
                "18.42"
            ],
            "Total Inventory": [
                "",
                "",
                ""
            ],
            "Total Current Assets": [
                "199.86",
                "84.35",
                "52.35"
            ],
            "Property Plant And Equipment - Gross": [
                "15.25",
                "12.47",
                "9.61"
            ],
            "Property Plant And Equipment - Net": [
                "15.07",
                "10.88",
                "8.81"
            ],
            "Goodwill Net": [
                "1309.75",
                "0.87",
                "0.74"
            ],
            "Intangibles Net": [
                "835.84",
                "",
                ""
            ],
            "Long Term Investments": [
                "",
                "",
                ""
            ],
            "Other Long Term Assets": [
                "",
                "",
                ""
            ],
            "Total Assets": [
                "2364.11",
                "99.90",
                "65.61"
            ],
            "Accounts Payable": [
                "124.51",
                "70.68",
                "24.80"
            ],
            "Accrued Expenses": [
                "55.00",
                "8.06",
                "24.46"
            ],
            "Notes Payable/Short Term Debt": [
                "3.58",
                "0.00",
                "0.00"
            ],
            "Current Port. of LT Debt/Capital Leases": [
                "0.05",
                "0.09",
                "1.63"
            ],
            "Other Current liabilities": [
                "",
                "",
                ""
            ],
            "Total Current Liabilities": [
                "198.77",
                "90.62",
                "54.57"
            ],
            "Long Term Debt": [
                "80.00",
                "45.39",
                "15.00"
            ],
            "Capital Lease Obligations": [
                "",
                "",
                ""
            ],
            "Total Long Term Debt": [
                "80.00",
                "45.39",
                "15.00"
            ],
            "Total Debt": [
                "83.62",
                "45.48",
                "16.63"
            ],
            "Other Liabilities": [
                "21.17",
                "9.95",
                "4.41"
            ],
            "Total Liabilities": [
                "2090.56",
                "127.77",
                "60.10"
            ],
            "Common Stock": [
                "0.02",
                "93.37",
                "89.32"
            ],
            "Additional Paid-In Capital": [
                "312.95",
                "",
                ""
            ],
            "Retained Earnings": [
                "-39.42",
                "-125.05",
                "-84.25"
            ],
            "Unrealized Gain (Loss)": [
                "",
                "",
                ""
            ],
            "Other Equity": [
                "",
                "",
                ""
            ],
            "Total Equity": [
                "273.55",
                "-27.87",
                "5.50"
            ],
            "Total Liabilities and Equity": [
                "2364.11",
                "99.90",
                "65.61"
            ],
            "Total Common Shares Outstanding": [
                "238.13",
                "243.60",
                "243.60"
            ],
            "Full-Time Employees": [
                "500",
                "450",
                ""
            ],
            "Number of Common Shareholders": [
                "36",
                "",
                ""
            ]
        },
        "Cash Flow": {
            "Dates": [
                "TTM",
                "12/31/2021",
                "12/31/2020",
                "12/31/2019",
                "12/31/2018"
            ],
            "Net Income": [
                "-1147.82",
                "-204.34",
                "-45.38"
            ],
            "Depreciation/Depletion": [
                "65.80",
                "1.73",
                "0.80"
            ],
            "Amortization": [
                "",
                "7.00",
                ""
            ],
            "Deferred Taxes": [
                "",
                "",
                ""
            ],
            "Non-Cash Items": [
                "883.21",
                "53.36",
                "-12.43"
            ],
            "Changes in Working Capital": [
                "71.11",
                "75.78",
                "32.42"
            ],
            "Cash from Operating Activities": [
                "-120.71",
                "-66.47",
                "-24.60"
            ],
            "Capital Expenditures": [
                "-2.70",
                "-3.41",
                "-2.93"
            ],
            "Other Investing Cash Flow Items": [
                "-53.26",
                "-52.65",
                "-0.24"
            ],
            "Cash from Investing Activities": [
                "-55.96",
                "-56.07",
                "-3.17"
            ],
            "Financing Cash Flow Items": [
                "",
                "",
                ""
            ],
            "Total Cash Dividends Paid": [
                "",
                "",
                ""
            ],
            "Issuance (Retirement) of Stock": [
                "195.31",
                "195.31",
                "-0.18"
            ],
            "Issuance (Retirement) of Debt": [
                "11.85",
                "28.16",
                "34.94"
            ],
            "Cash from Financing Activities": [
                "207.35",
                "223.47",
                "34.76"
            ],
            "Foreign Exchange Effects": [
                "",
                "",
                ""
            ],
            "Net Cash - Beginning Balance": [
                "",
                "45.26",
                "32.90"
            ],
            "Net Cash - Ending Balance": [
                "",
                "146.19",
                "39.90"
            ],
            "Net Change in Cash": [
                "30.68",
                "100.93",
                "7.00"
            ],
            "Cash Interest Paid": [
                "4.14",
                "4.14",
                "0.69"
            ],
            "Cash Taxes Paid": [
                "",
                "",
                ""
            ]
        }
    }
}